imgur_uploader.py
imgur_uploader-0.3.0.dist-info/METADATA
imgur_uploader-0.3.0.dist-info/RECORD
imgur_uploader-0.3.0.dist-info/WHEEL
imgur_uploader-0.3.0.dist-info/entry_points.txt
imgur_uploader-0.3.0.dist-info/top_level.txt
