Metadata-Version: 1.1
Name: imgur-uploader
Version: 0.3.0
Summary: A simple command line client for uploading files to Imgur.
Home-page: https://github.com/atbaker/imgur-uploader
Author: Andrew Tork Baker
Author-email: andrew@atbaker.me
License: MIT
Platform: UNKNOWN
Classifier: Development Status :: 5 - Production/Stable
Classifier: Intended Audience :: Developers
Classifier: Natural Language :: English
Classifier: License :: OSI Approved :: MIT License
Classifier: Operating System :: OS Independent
Classifier: Programming Language :: Python
Classifier: Programming Language :: Python :: 2
Classifier: Programming Language :: Python :: 2.7
Classifier: Programming Language :: Python :: 3
Classifier: Programming Language :: Python :: 3.3
Classifier: Programming Language :: Python :: 3.4
Classifier: Topic :: Utilities
